python/__init__.py
python/potato.py
potatopy-1.0.0.dist-info/LICENSE
potatopy-1.0.0.dist-info/METADATA
potatopy-1.0.0.dist-info/WHEEL
potatopy-1.0.0.dist-info/top_level.txt
potatopy-1.0.0.dist-info/RECORD
