Metadata-Version: 2.2
Name: potatopy
Version: 1.0.0
Summary: A simple Template for create python project
Home-page: https://github.com/potatoscript/potatopy
Author: potatoscript
Author-email: potatoscript@hotmail.com
Classifier: Programming Language :: Python :: 3
Classifier: License :: OSI Approved :: MIT License
Classifier: Operating System :: OS Independent
Requires-Python: >=3.6
License-File: LICENSE
Dynamic: author
Dynamic: author-email
Dynamic: classifier
Dynamic: description
Dynamic: description-content-type
Dynamic: home-page
Dynamic: requires-python
Dynamic: summary
